image_file_name_fixer/__init__.py
image_file_name_fixer/__main__.py
image_file_name_fixer/app_config.py
image_file_name_fixer/argument_processor.py
image_file_name_fixer/file_utils.py
image_file_name_fixer/format_mapper.py
image_file_name_fixer/image_details.py
image_file_name_fixer/image_resolution.py
image_file_name_fixer/name_fixer.py
image_file_name_fixer-0.10.1.dist-info/LICENSE.md
image_file_name_fixer-0.10.1.dist-info/METADATA
image_file_name_fixer-0.10.1.dist-info/WHEEL
image_file_name_fixer-0.10.1.dist-info/entry_points.txt
image_file_name_fixer-0.10.1.dist-info/top_level.txt
image_file_name_fixer-0.10.1.dist-info/RECORD
