Metadata-Version: 2.1
Name: image-file-name-fixer
Version: 0.10.1
Summary: Image File Name Fixer
Home-page: https://gitlab.com/jeremymreed/image-file-name-fixer
Author: Jeremy Reed
Author-email: reeje76@gmail.com
License: MIT
Platform: UNKNOWN
